packeteer/__init__.py
packeteer/fields.py
packeteer/packets.py
tests/values/__init__.py
tests/values/simple.py
tests/values/string.py
packeteer-0.4.dist-info/LICENSE
packeteer-0.4.dist-info/METADATA
packeteer-0.4.dist-info/WHEEL
packeteer-0.4.dist-info/top_level.txt
packeteer-0.4.dist-info/RECORD
