Metadata-Version: 2.1
Name: packeteer
Version: 0.4
Summary: Light-weight packet serializer
Home-page: https://github.com/lungdart/packeteer
Author: lungdart
Author-email: dev@lungdart.net
License: MIT
Platform: UNKNOWN
Classifier: License :: OSI Approved :: MIT License
Classifier: Natural Language :: English
Classifier: Operating System :: POSIX
Classifier: Programming Language :: Python
Classifier: Programming Language :: Python :: 2
Classifier: Programming Language :: Python :: 2.7
Classifier: Programming Language :: Python :: 3
Classifier: Programming Language :: Python :: 3.5
Classifier: Programming Language :: Python :: 3.6
Classifier: Programming Language :: Python :: 3.7
Classifier: Programming Language :: Python :: Implementation :: CPython
Classifier: Topic :: System :: Networking
Classifier: Intended Audience :: Developers
Requires-Python: >=2.7.0
Requires-Dist: future
Requires-Dist: six
